torch_geometric/__init__.py
torch_geometric/_compile.py
torch_geometric/_onnx.py
torch_geometric/backend.py
torch_geometric/config_mixin.py
torch_geometric/config_store.py
torch_geometric/debug.py
torch_geometric/deprecation.py
torch_geometric/device.py
torch_geometric/edge_index.py
torch_geometric/experimental.py
torch_geometric/hash_tensor.py
torch_geometric/home.py
torch_geometric/index.py
torch_geometric/inspector.py
torch_geometric/isinstance.py
torch_geometric/lazy_loader.py
torch_geometric/logging.py
torch_geometric/resolver.py
torch_geometric/seed.py
torch_geometric/template.py
torch_geometric/typing.py
torch_geometric/warnings.py
torch_geometric/contrib/__init__.py
torch_geometric/contrib/datasets/__init__.py
torch_geometric/contrib/explain/__init__.py
torch_geometric/contrib/explain/pgm_explainer.py
torch_geometric/contrib/nn/__init__.py
torch_geometric/contrib/nn/conv/__init__.py
torch_geometric/contrib/nn/models/__init__.py
torch_geometric/contrib/nn/models/rbcd_attack.py
torch_geometric/contrib/transforms/__init__.py
torch_geometric/data/__init__.py
torch_geometric/data/batch.py
torch_geometric/data/collate.py
torch_geometric/data/data.py
torch_geometric/data/database.py
torch_geometric/data/datapipes.py
torch_geometric/data/dataset.py
torch_geometric/data/download.py
torch_geometric/data/extract.py
torch_geometric/data/feature_store.py
torch_geometric/data/graph_store.py
torch_geometric/data/hetero_data.py
torch_geometric/data/hypergraph_data.py
torch_geometric/data/in_memory_dataset.py
torch_geometric/data/makedirs.py
torch_geometric/data/on_disk_dataset.py
torch_geometric/data/remote_backend_utils.py
torch_geometric/data/separate.py
torch_geometric/data/storage.py
torch_geometric/data/summary.py
torch_geometric/data/temporal.py
torch_geometric/data/view.py
torch_geometric/data/lightning/__init__.py
torch_geometric/data/lightning/datamodule.py
torch_geometric/datasets/__init__.py
torch_geometric/datasets/actor.py
torch_geometric/datasets/airfrans.py
pyg_nightly-2.8.0.dev20260201.dist-info/licenses/LICENSE
pyg_nightly-2.8.0.dev20260201.dist-info/WHEEL
pyg_nightly-2.8.0.dev20260201.dist-info/METADATA
pyg_nightly-2.8.0.dev20260201.dist-info/RECORD
