Metadata-Version: 2.4
Name: pyg-nightly
Version: 2.8.0.dev20260201
Summary: Graph Neural Network Library for PyTorch
Keywords: deep-learning,pytorch,geometric-deep-learning,graph-neural-networks,graph-convolutional-networks
Author-email: Matthias Fey <matthias@pyg.org>
Requires-Python: >=3.10
License-Expression: MIT
Classifier: Development Status :: 5 - Production/Stable
Classifier: Programming Language :: Python
Classifier: Programming Language :: Python :: 3.10
Classifier: Programming Language :: Python :: 3.11
Classifier: Programming Language :: Python :: 3.12
Classifier: Programming Language :: Python :: 3.13
Classifier: Programming Language :: Python :: 3 :: Only
License-File: LICENSE
Requires-Dist: aiohttp
Requires-Dist: fsspec
Requires-Dist: jinja2
Requires-Dist: numpy
Requires-Dist: psutil>=5.8.0
Requires-Dist: pyparsing
Requires-Dist: requests
Requires-Dist: tqdm
Requires-Dist: xxhash
Requires-Dist: matplotlib ; extra == "benchmark"
Requires-Dist: networkx ; extra == "benchmark"
Requires-Dist: pandas ; extra == "benchmark"
Requires-Dist: protobuf<4.21 ; extra == "benchmark"
Requires-Dist: wandb ; extra == "benchmark"
Requires-Dist: ipython ; extra == "dev"
Requires-Dist: matplotlib-inline ; extra == "dev"
Requires-Dist: pre-commit ; extra == "dev"
Requires-Dist: torch_geometric[test] ; extra == "dev"
Requires-Dist: scipy ; extra == "full"
Requires-Dist: scikit-learn ; extra == "full"
Requires-Dist: ase ; extra == "full"
Requires-Dist: captum<0.7.0 ; extra == "full"
Requires-Dist: graphviz ; extra == "full"
Requires-Dist: h5py ; extra == "full"
Requires-Dist: matplotlib ; extra == "full"
Requires-Dist: networkx ; extra == "full"
Requires-Dist: numba<0.60.0 ; extra == "full"
Requires-Dist: opt_einsum ; extra == "full"
Requires-Dist: pandas ; extra == "full"
Requires-Dist: pynndescent ; extra == "full"
Requires-Dist: pytorch-memlab ; extra == "full"
Requires-Dist: rdflib ; extra == "full"
Requires-Dist: rdkit ; extra == "full"
Requires-Dist: scikit-image ; extra == "full"
Requires-Dist: statsmodels ; extra == "full"
Requires-Dist: sympy ; extra == "full"
Requires-Dist: tabulate ; extra == "full"
Requires-Dist: torch_geometric[graphgym, modelhub] ; extra == "full"
Requires-Dist: torchmetrics ; extra == "full"
Requires-Dist: trimesh ; extra == "full"
Requires-Dist: protobuf<4.21 ; extra == "graphgym"
Requires-Dist: pytorch-lightning ; extra == "graphgym"
Requires-Dist: yacs ; extra == "graphgym"
Requires-Dist: huggingface_hub ; extra == "modelhub"
Requires-Dist: pcst_fast ; extra == "rag"
Requires-Dist: datasets ; extra == "rag"
Requires-Dist: transformers ; extra == "rag"
Requires-Dist: pandas ; extra == "rag"
Requires-Dist: sentencepiece ; extra == "rag"
Requires-Dist: accelerate ; extra == "rag"
Requires-Dist: torchmetrics ; extra == "rag"
Requires-Dist: onnx ; extra == "test"
Requires-Dist: onnxruntime ; extra == "test"
Requires-Dist: onnxscript ; extra == "test"
Requires-Dist: pytest ; extra == "test"
Requires-Dist: pytest-cov ; extra == "test"
Project-URL: changelog, https://github.com/pyg-team/pytorch_geometric/blob/master/CHANGELOG.md
Project-URL: documentation, https://pytorch-geometric.readthedocs.io
Project-URL: homepage, https://pyg.org
Project-URL: repository, https://github.com/pyg-team/pytorch_geometric.git
Provides-Extra: benchmark
Provides-Extra: dev
Provides-Extra: full
Provides-Extra: graphgym
Provides-Extra: modelhub
Provides-Extra: rag
Provides-Extra: test
